setup.py
SpockPy.egg-info/PKG-INFO
SpockPy.egg-info/SOURCES.txt
SpockPy.egg-info/dependency_links.txt
SpockPy.egg-info/requires.txt
SpockPy.egg-info/top_level.txt
spockpy/__init__.py
spockpy/config.py
spockpy/log.py
spockpy/utils/__init__.py
spockpy/utils/getcallargs.py
spockpy/utils/misc.py