Metadata-Version: 1.0
Name: SpockPy
Version: 0.0.2.5
Summary: Spocks misc scripts
Home-page: UNKNOWN
Author: Erik Gafni
Author-email: UNKNOWN
License: Non-commercial
Platform: UNKNOWN
